odoo/addons/mrp_stock_picking_restrict_cancel/README.rst
odoo/addons/mrp_stock_picking_restrict_cancel/__init__.py
odoo/addons/mrp_stock_picking_restrict_cancel/__manifest__.py
odoo/addons/mrp_stock_picking_restrict_cancel/i18n/mrp_stock_picking_restrict_cancel.pot
odoo/addons/mrp_stock_picking_restrict_cancel/models/__init__.py
odoo/addons/mrp_stock_picking_restrict_cancel/models/stock_move.py
odoo/addons/mrp_stock_picking_restrict_cancel/readme/CONTRIBUTORS.rst
odoo/addons/mrp_stock_picking_restrict_cancel/readme/DESCRIPTION.rst
odoo/addons/mrp_stock_picking_restrict_cancel/static/description/icon.png
odoo/addons/mrp_stock_picking_restrict_cancel/static/description/index.html
odoo11_addon_mrp_stock_picking_restrict_cancel-11.0.1.0.1.99.dev7.dist-info/METADATA
odoo11_addon_mrp_stock_picking_restrict_cancel-11.0.1.0.1.99.dev7.dist-info/WHEEL
odoo11_addon_mrp_stock_picking_restrict_cancel-11.0.1.0.1.99.dev7.dist-info/top_level.txt
odoo11_addon_mrp_stock_picking_restrict_cancel-11.0.1.0.1.99.dev7.dist-info/RECORD
